tap_openproject/__init__.py
tap_openproject/schemas/projects.json
tap_openproject/schemas/work_packages.json
tap_openproject/streams.py
tap_openproject/tap.py
tap_openproject-0.2.3.dist-info/METADATA
tap_openproject-0.2.3.dist-info/WHEEL
tap_openproject-0.2.3.dist-info/entry_points.txt
tap_openproject-0.2.3.dist-info/licenses/LICENSE
tap_openproject-0.2.3.dist-info/RECORD
