Metadata-Version: 2.4
Name: tap-openproject
Version: 0.2.3
Summary: Singer tap for OpenProject API - Built with the Meltano Singer SDK
License: MIT
License-File: LICENSE
Keywords: singer,tap,openproject,etl,meltano,sdk
Author: surveilr Team
Author-email: support@surveilr.com
Requires-Python: >=3.8,<4.0
Classifier: Development Status :: 4 - Beta
Classifier: Intended Audience :: Developers
Classifier: License :: OSI Approved :: MIT License
Classifier: Operating System :: OS Independent
Classifier: Programming Language :: Python :: 3
Classifier: Programming Language :: Python :: 3.8
Classifier: Programming Language :: Python :: 3.9
Classifier: Programming Language :: Python :: 3.10
Classifier: Programming Language :: Python :: 3.11
Classifier: Programming Language :: Python :: 3.12
Classifier: Programming Language :: Python :: 3.13
Classifier: Programming Language :: Python :: 3.14
Classifier: Topic :: Software Development :: Libraries :: Python Modules
Requires-Dist: requests (>=2.31.0,<3.0.0)
Requires-Dist: singer-sdk (>=0.39.0,<0.40.0)
Project-URL: Documentation, https://github.com/netspective-labs/tap-openproject#readme
Project-URL: Homepage, https://github.com/netspective-labs/tap-openproject#readme
Project-URL: Repository, https://github.com/netspective-labs/tap-openproject
